sqlranger/__init__.py
sqlranger/checker.py
sqlranger-0.0.3.dist-info/METADATA
sqlranger-0.0.3.dist-info/WHEEL
sqlranger-0.0.3.dist-info/licenses/LICENSE
sqlranger-0.0.3.dist-info/RECORD
