Metadata-Version: 2.4
Name: sqlranger
Version: 0.0.3
Summary: SQL Ranger: Enforcer of partitioning or finite-range check presence in SQL Queries
License: MIT
License-File: LICENSE
Author: Dmitry Spikhalsky
Author-email: dmitry@spikhalskiy.com
Requires-Python: >=3.10
Classifier: Development Status :: 2 - Pre-Alpha
Classifier: Intended Audience :: Developers
Classifier: License :: OSI Approved :: MIT License
Classifier: Operating System :: OS Independent
Classifier: Programming Language :: Python :: 3
Classifier: Programming Language :: Python :: 3.10
Classifier: Programming Language :: Python :: 3.11
Classifier: Programming Language :: Python :: 3.12
Classifier: Programming Language :: Python :: 3.13
Classifier: Programming Language :: Python :: 3.14
Classifier: Programming Language :: Python :: 3 :: Only
Classifier: Programming Language :: SQL
Requires-Dist: sqlglot (>=28.0.0)
Project-URL: Issues, https://github.com/Spikhalskiy/sql-ranger/issues
Project-URL: Repository, https://github.com/Spikhalskiy/sql-ranger
